mailgunlog/__init__.py
mailgunlog/__main__.py
mailgunlog/mailgunlog.py
mailgunlog-0.0.3.data/scripts/mailgunlog
mailgunlog-0.0.3.dist-info/DESCRIPTION.rst
mailgunlog-0.0.3.dist-info/entry_points.txt
mailgunlog-0.0.3.dist-info/METADATA
mailgunlog-0.0.3.dist-info/pydist.json
mailgunlog-0.0.3.dist-info/RECORD
mailgunlog-0.0.3.dist-info/top_level.txt
mailgunlog-0.0.3.dist-info/WHEEL
