Metadata-Version: 2.0
Name: mailgunlog
Version: 0.0.3
Summary: Mailgun Log
Home-page: https://github.com/getupcloud/python-mailgunlog
Author: Getup Cloud
Author-email: mateus.caruccio@getupcloud.com
License: Apache Software License
Keywords: mailgun log email mail
Platform: UNKNOWN
Classifier: Development Status :: 4 - Beta
Classifier: Intended Audience :: Developers
Classifier: Topic :: Software Development :: Build Tools
Classifier: License :: OSI Approved :: Apache Software License
Classifier: Programming Language :: Python :: 2
Classifier: Programming Language :: Python :: 2.6
Classifier: Programming Language :: Python :: 2.7
Requires-Dist: requests (>=2.0.0)
Requires-Dist: python-dateutil (>=2.2)
